bpm/__init__.py
bpm/bambucommands.py
bpm/bambuconfig.py
bpm/bambuprinter.py
bpm/bambuspool.py
bpm/bambutools.py
bpm/ftpsclient/__init__.py
bpm/ftpsclient/ftpsclient.py
bambu_printer_manager-0.5.4.dist-info/LICENSE
bambu_printer_manager-0.5.4.dist-info/METADATA
bambu_printer_manager-0.5.4.dist-info/WHEEL
bambu_printer_manager-0.5.4.dist-info/top_level.txt
bambu_printer_manager-0.5.4.dist-info/RECORD
