Metadata-Version: 2.2
Name: bambu-printer-manager
Version: 0.5.4
Summary: A pure python library for managing Bambu Labs printers
Author-email: "Shell M. Shrader" <shell@shellware.com>
Project-URL: Homepage, https://github.com/synman/bambu-printer-manager
Project-URL: Documentation, https://synman.github.io/bambu-printer-manager/
Project-URL: Issues, https://github.com/synman/bambu-printer-manager/issues
Classifier: Programming Language :: Python :: 3
Classifier: License :: Freely Distributable
Classifier: Operating System :: OS Independent
Requires-Python: >=3.11
License-File: LICENSE
Requires-Dist: webcolors
Requires-Dist: paho-mqtt
Requires-Dist: typing-extensions; python_version < "3.12"
Provides-Extra: develop
Requires-Dist: pre-commit; extra == "develop"
Provides-Extra: docs
Requires-Dist: mkdocstrings[python]>=0.18; extra == "docs"
